{
  "textures": {
    "particle": "voidheart:block/portal",
    "portal": "voidheart:block/portal",
    "backface": "voidheart:block/portal/portal_interior_veins"
  },
  "elements": [
    {
      "from": [
        0,
        0,
        6
      ],
      "to": [
        16,
        16,
        10
      ],
      "faces": {
        "north": {
          "uv": [
            0,
            0,
            16,
            16
          ],
          "texture": "#portal"
        }
      }
    },
    {
      "from": [
        0,
        0,
        11
      ],
      "to": [
        16,
        16,
        16
      ],
      "faces": {
        "north": {
          "uv": [
            0,
            0,
            16,
            16
          ],
          "texture": "#backface"
        },
        "south": {
          "uv": [
            0,
            0,
            16,
            16
          ],
          "texture": "#backface"
        }
      }
    }
  ]
}